{
	"manifest_version": 2,
	"name": "Better Formula Editor for Anaplan",
	"version": "3.0.3",
	"description": "This addon enhances Anaplan formula editing in several ways; providing code completion, hover info and validity checks.",
	"icons": {
		"128": "logo.drawio.png"
	},
	"content_scripts": [
		{
			"matches": [
				"https://*.app.anaplan.com/*"
			],
			"js": [
				"/bin/content-script.js"
			],
			"run_at": "document_end",
			"all_frames": true
		}
	],
	"permissions": [
		"https://*.app.anaplan.com/*/anaplan/*",
		"https://*.app.anaplan.com/a/modeling/*"
	],
	"web_accessible_resources": [
		"bin/*"
	]
}